[{"id":392,"brand":"泛泰","modelName":"A770K","alias":"","resolutionRatio":"480x800","api":"10","cpu":"高通","cpuDetail":"MSM8660","modelSerial":"IM-A770K","status":1},{"id":391,"brand":"泛泰","modelName":"A820L","alias":"","resolutionRatio":"800x1280","api":"9","cpu":"高通","cpuDetail":"MSM8660","modelSerial":"IM-A820L","status":1},{"id":396,"brand":"泛泰","modelName":"Breakout","alias":"","resolutionRatio":"480x800","api":"10","cpu":"德州仪器TI OMAP","cpuDetail":"OMAP3420","modelSerial":"","status":1},{"id":397,"brand":"泛泰","modelName":"Crossover","alias":"","resolutionRatio":"320x480","api":"8","cpu":"德州仪器TI OMAP","cpuDetail":"OMAP3630","modelSerial":"","status":1},{"id":393,"brand":"泛泰","modelName":"IS06","alias":"","resolutionRatio":"480x800","api":"8","cpu":"高通","cpuDetail":"QSD8250","modelSerial":"","status":1},{"id":401,"brand":"泛泰","modelName":"Mirach A","alias":"","resolutionRatio":"320x480","api":"10","cpu":"德州仪器TI OMAP","cpuDetail":"OMAP3630","modelSerial":"","status":1},{"id":399,"brand":"泛泰","modelName":"Vega IM-A650S","alias":"","resolutionRatio":"480x800","api":"7","cpu":"高通","cpuDetail":"QSD8250","modelSerial":"","status":1},{"id":395,"brand":"泛泰","modelName":"Vega LTE","alias":"","resolutionRatio":"800x1280","api":"10","cpu":"高通","cpuDetail":"MSM8960","modelSerial":"","status":1},{"id":398,"brand":"泛泰","modelName":"Vega No.5","alias":"IM-T100K","resolutionRatio":"480x800","api":"10","cpu":"高通","cpuDetail":"MSM8660","modelSerial":"IM-T100K","status":1},{"id":1646,"brand":"泛泰","modelName":"Vega R3 ","alias":"","resolutionRatio":"720x1280","api":"16","cpu":"高通","cpuDetail":"APQ8064","modelSerial":"IM-A850K,IM-A850S,IM-A850L","status":1},{"id":400,"brand":"泛泰","modelName":"Vega Racer","alias":"","resolutionRatio":"480x800","api":"10","cpu":"高通","cpuDetail":"MSM8660","modelSerial":"","status":1},{"id":1647,"brand":"泛泰","modelName":"Vega S5","alias":"IM-A840S","resolutionRatio":"720x1280","api":"14","cpu":"高通","cpuDetail":"MSM8960","modelSerial":"IM-A840S","status":1},{"id":394,"brand":"泛泰","modelName":"Vega X","alias":"","resolutionRatio":"320x480","api":"8","cpu":"高通","cpuDetail":"MSM8255","modelSerial":"","status":1}]